Metadata-Version: 1.0
Name: gaus-bin-distributions-foba
Version: 0.1
Summary: Gaussian and binomial distributions foba
Home-page: UNKNOWN
Author: Fiyinfoba Ogunkeye
Author-email: fobaogunkeye@gmail.com
License: UNKNOWN
Platform: UNKNOWN
